didwegivecredit/__init__.py
didwegivecredit/cli.py
didwegivecredit/didwegivecredit.py
didwegivecredit-0.0.2.dist-info/LICENSE
didwegivecredit-0.0.2.dist-info/METADATA
didwegivecredit-0.0.2.dist-info/WHEEL
didwegivecredit-0.0.2.dist-info/entry_points.txt
didwegivecredit-0.0.2.dist-info/top_level.txt
didwegivecredit-0.0.2.dist-info/RECORD
