Metadata-Version: 2.1
Name: didwegivecredit
Version: 0.0.2
Summary: A small linter that checks whether committers to a repository are acknowledged with all-contributors
Home-page: https://github.com/adswa/didwegivecredit
Author: Adina Wagner
Author-email: adina.wagner@t-online.de
License: MIT license
Keywords: didwegivecredit
Platform: UNKNOWN
Classifier: Development Status :: 2 - Pre-Alpha
Classifier: Intended Audience :: Developers
Classifier: License :: OSI Approved :: MIT License
Classifier: Natural Language :: English
Classifier: Programming Language :: Python :: 3
Classifier: Programming Language :: Python :: 3.5
Classifier: Programming Language :: Python :: 3.6
Classifier: Programming Language :: Python :: 3.7
Classifier: Programming Language :: Python :: 3.8
Requires-Python: >=3.5
Requires-Dist: rich
Requires-Dist: fuzzywuzzy
